fiduswriter/languagetool/__init__.py
fiduswriter/languagetool/apps.py
fiduswriter/languagetool/urls.py
fiduswriter/languagetool/views.py
fiduswriter/languagetool/locale/bg/LC_MESSAGES/djangojs.mo
fiduswriter/languagetool/locale/bg/LC_MESSAGES/djangojs.po
fiduswriter/languagetool/locale/de/LC_MESSAGES/djangojs.mo
fiduswriter/languagetool/locale/de/LC_MESSAGES/djangojs.po
fiduswriter/languagetool/locale/es/LC_MESSAGES/djangojs.mo
fiduswriter/languagetool/locale/es/LC_MESSAGES/djangojs.po
fiduswriter/languagetool/locale/fr/LC_MESSAGES/djangojs.mo
fiduswriter/languagetool/locale/fr/LC_MESSAGES/djangojs.po
fiduswriter/languagetool/locale/it/LC_MESSAGES/djangojs.mo
fiduswriter/languagetool/locale/it/LC_MESSAGES/djangojs.po
fiduswriter/languagetool/locale/pt_BR/LC_MESSAGES/djangojs.mo
fiduswriter/languagetool/locale/pt_BR/LC_MESSAGES/djangojs.po
fiduswriter/languagetool/static/js/modules/lt/dialog.js
fiduswriter/languagetool/static/js/modules/lt/editor.js
fiduswriter/languagetool/static/js/modules/lt/state_plugin.js
fiduswriter/languagetool/static/js/modules/lt/templates.js
fiduswriter/languagetool/static/js/plugins/editor/lt.js
fiduswriter/languagetool/tests/__init__.py
fiduswriter/languagetool/tests/test_languagetool.py
fiduswriter_languagetool-4.0.0.dist-info/licenses/LICENSE
fiduswriter_languagetool-4.0.0.dist-info/METADATA
fiduswriter_languagetool-4.0.0.dist-info/WHEEL
fiduswriter_languagetool-4.0.0.dist-info/top_level.txt
fiduswriter_languagetool-4.0.0.dist-info/RECORD
